MANIFEST.in
README.rst
common.py
git-jira-attacher.py
jira-am
jira-apply
setup.py
git_jira_attacher.egg-info/PKG-INFO
git_jira_attacher.egg-info/SOURCES.txt
git_jira_attacher.egg-info/dependency_links.txt
git_jira_attacher.egg-info/requires.txt
git_jira_attacher.egg-info/top_level.txt