Metadata-Version: 1.0
Name: git-jira-attacher
Version: 0.1
Summary: Utility for integrating Git and JIRA workflows
Home-page: http://github.com/dreiss/git-jira-attacher/tree
Author: Michael Greene
Author-email: michael.greene@gmail.com
License: MIT License
Platform: UNKNOWN
Classifier: Development Status :: 4 - Beta
Classifier: Intended Audience :: Developers
Classifier: License :: OSI Approved :: MIT License
Classifier: Operating System :: POSIX
Classifier: Topic :: Software Development :: Bug Tracking
Classifier: Topic :: Software Development :: Version Control
